easy_splunk/__init__.py
easy_splunk/easy_splunk.py
easy_splunk-0.2.0.dist-info/LICENSE
easy_splunk-0.2.0.dist-info/METADATA
easy_splunk-0.2.0.dist-info/WHEEL
easy_splunk-0.2.0.dist-info/top_level.txt
easy_splunk-0.2.0.dist-info/RECORD
