Metadata-Version: 2.1
Name: easy-splunk
Version: 0.2.0
Summary: A simple and complete package to abstract main operations with Splunk API (send data / run search / get result)
Home-page: https://github.com/alissonpdc/pysplunk
Author: Alisson Prado da Cruz
Author-email: alissonpdc@gmail.com
License: UNKNOWN
Keywords: splunk
Platform: UNKNOWN
Classifier: Development Status :: 3 - Alpha
Classifier: Programming Language :: Python :: 2
Classifier: Programming Language :: Python :: 2.7
Classifier: Programming Language :: Python :: 3
Classifier: Programming Language :: Python :: 3.4
Classifier: Programming Language :: Python :: 3.5
Classifier: Programming Language :: Python :: 3.6
Classifier: Programming Language :: Python :: 3.7
Classifier: License :: OSI Approved :: MIT License
Classifier: Operating System :: OS Independent
Requires-Python: >=2.7, !=3.0.*, !=3.1.*, !=3.2.*, !=3.3.*
